Metadata-Version: 2.1
Name: chessai-python
Version: 0.0.2
Summary: ChessAI - Chinese Chess Game Analyzer
Home-page: https://github.com/vietanhdev/chessai
Author: Viet-Anh Nguyen
Author-email: vietanh.dev@gmail.com
License: GPLv3+
Keywords: Chess,XiangQi,Chinese Chess,AI,Analysis
Classifier: Natural Language :: English
Classifier: Operating System :: OS Independent
Classifier: Programming Language :: Python
Classifier: Programming Language :: Python :: 3.8
Classifier: Programming Language :: Python :: 3.9
Classifier: Programming Language :: Python :: 3.10
Classifier: Programming Language :: Python :: 3.11
Classifier: Programming Language :: Python :: 3 :: Only
Requires-Dist: urllib3 >=2.0.2
Requires-Dist: extract-msg >=0.41.1
Requires-Dist: tabulate >=0.9.0
Requires-Dist: python-multipart >=0.0.6
Requires-Dist: fastapi ==0.96.0
Requires-Dist: SQLAlchemy ==2.0.15
Requires-Dist: alembic ==1.11.1
Requires-Dist: requests ==2.31.0
Requires-Dist: uvicorn ==0.23.2
Requires-Dist: PyYAML ==6.0.1
Requires-Dist: psutil ==5.9.6
Requires-Dist: python-on-whales ==0.65.0
Requires-Dist: tk ==0.1.0
Requires-Dist: pywebview ==4.4.1
Requires-Dist: opencv-contrib-python ==4.7.0.72
Requires-Dist: imutils ==0.5.4
Requires-Dist: pyserial ==3.5
Requires-Dist: pyinstaller ==5.13.2
Requires-Dist: svglib ==1.5.1
Requires-Dist: reportlab ==4.0.4
Requires-Dist: serial ==0.0.97
